image_bucket/__init__.py
image_bucket/image_bucket.py
image_bucket-0.1.dist-info/METADATA
image_bucket-0.1.dist-info/WHEEL
image_bucket-0.1.dist-info/entry_points.txt
image_bucket-0.1.dist-info/top_level.txt
image_bucket-0.1.dist-info/RECORD
