Metadata-Version: 2.1
Name: image-bucket
Version: 0.1
Summary: UNKNOWN
Home-page: UNKNOWN
Author: UNKNOWN
Author-email: UNKNOWN
License: UNKNOWN
Platform: UNKNOWN
Requires-Dist: opencv-python (==4.10.0.82)
